{
  "name": "SpotiFLAC Custom Store",
  "version": "1.0.0",
  "description": "Custom SpotiFLAC extension registry",
  "extensions": [
    {
      "id": "openlyrics",
      "display_name": "OpenLyrics",
      "description": "Lyrics provider for SpotiFLAC.",
      "author": "abhishekkr20",
      "version": "1.0.0",
      "category": "lyrics",
      "download_url": "extensions/openlyrics.spotiflac-ext",
      "icon": "icons/lyrics.png"
    },
    {
      "id": "utility-tools",
      "display_name": "Utility Functions",
      "description": "Utilities for metadata, filenames and helper tools.",
      "author": "abhishekkr20",
      "version": "1.0.0",
      "category": "utility",
      "download_url": "extensions/utility-tools.spotiflac-ext",
      "icon": "icons/utility.png"
    }
  ]
}
